{
  "generated_at": "2026-04-13T14:06:07",
  "zones": [
    {
      "id": "north",
      "name": "North End",
      "lat": 47.64,
      "lon": -122.092,
      "time": "2026-04-13T14:00",
      "wind_mph": 8.7,
      "wind_dir_deg": 247,
      "gust_mph": 15.0,
      "effective_wind_mph": 8.7,
      "chop_score": 20,
      "chop_label": "Too Rough",
      "hourly": [
        {
          "time": "2026-04-13T14:00",
          "wind_mph": 8.7,
          "wind_dir_deg": 247,
          "gust_mph": 15.0,
          "effective_wind_mph": 8.7,
          "chop_score": 20,
          "chop_label": "Too Rough"
        },
        {
          "time": "2026-04-13T15:00",
          "wind_mph": 6.6,
          "wind_dir_deg": 280,
          "gust_mph": 12.3,
          "effective_wind_mph": 4.2,
          "chop_score": 84,
          "chop_label": "Glass"
        },
        {
          "time": "2026-04-13T16:00",
          "wind_mph": 6.3,
          "wind_dir_deg": 268,
          "gust_mph": 11.9,
          "effective_wind_mph": 4.0,
          "chop_score": 85,
          "chop_label": "Glass"
        },
        {
          "time": "2026-04-13T17:00",
          "wind_mph": 8.6,
          "wind_dir_deg": 261,
          "gust_mph": 15.2,
          "effective_wind_mph": 5.5,
          "chop_score": 81,
          "chop_label": "Glass"
        },
        {
          "time": "2026-04-13T18:00",
          "wind_mph": 8.4,
          "wind_dir_deg": 261,
          "gust_mph": 15.4,
          "effective_wind_mph": 5.4,
          "chop_score": 80,
          "chop_label": "Glass"
        }
      ]
    },
    {
      "id": "ne_shore",
      "name": "NE Shore",
      "lat": 47.622,
      "lon": -122.078,
      "time": "2026-04-13T14:00",
      "wind_mph": 9.3,
      "wind_dir_deg": 246,
      "gust_mph": 15.7,
      "effective_wind_mph": 9.3,
      "chop_score": 16,
      "chop_label": "Too Rough",
      "hourly": [
        {
          "time": "2026-04-13T14:00",
          "wind_mph": 9.3,
          "wind_dir_deg": 246,
          "gust_mph": 15.7,
          "effective_wind_mph": 9.3,
          "chop_score": 16,
          "chop_label": "Too Rough"
        },
        {
          "time": "2026-04-13T15:00",
          "wind_mph": 7.9,
          "wind_dir_deg": 260,
          "gust_mph": 13.2,
          "effective_wind_mph": 7.9,
          "chop_score": 53,
          "chop_label": "Choppy"
        },
        {
          "time": "2026-04-13T16:00",
          "wind_mph": 7.8,
          "wind_dir_deg": 258,
          "gust_mph": 13.4,
          "effective_wind_mph": 7.8,
          "chop_score": 52,
          "chop_label": "Choppy"
        },
        {
          "time": "2026-04-13T17:00",
          "wind_mph": 9.1,
          "wind_dir_deg": 259,
          "gust_mph": 16.1,
          "effective_wind_mph": 9.1,
          "chop_score": 44,
          "chop_label": "Choppy"
        },
        {
          "time": "2026-04-13T18:00",
          "wind_mph": 8.6,
          "wind_dir_deg": 261,
          "gust_mph": 15.7,
          "effective_wind_mph": 8.6,
          "chop_score": 46,
          "chop_label": "Choppy"
        }
      ]
    },
    {
      "id": "mid_west",
      "name": "The Cove",
      "lat": 47.612,
      "lon": -122.102,
      "time": "2026-04-13T14:00",
      "wind_mph": 9.3,
      "wind_dir_deg": 246,
      "gust_mph": 15.7,
      "effective_wind_mph": 4.8,
      "chop_score": 96,
      "chop_label": "Glass",
      "hourly": [
        {
          "time": "2026-04-13T14:00",
          "wind_mph": 9.3,
          "wind_dir_deg": 246,
          "gust_mph": 15.7,
          "effective_wind_mph": 4.8,
          "chop_score": 96,
          "chop_label": "Glass"
        },
        {
          "time": "2026-04-13T15:00",
          "wind_mph": 7.9,
          "wind_dir_deg": 260,
          "gust_mph": 13.2,
          "effective_wind_mph": 3.6,
          "chop_score": 99,
          "chop_label": "Glass"
        },
        {
          "time": "2026-04-13T16:00",
          "wind_mph": 7.8,
          "wind_dir_deg": 258,
          "gust_mph": 13.4,
          "effective_wind_mph": 3.6,
          "chop_score": 99,
          "chop_label": "Glass"
        },
        {
          "time": "2026-04-13T17:00",
          "wind_mph": 9.1,
          "wind_dir_deg": 259,
          "gust_mph": 16.1,
          "effective_wind_mph": 4.2,
          "chop_score": 98,
          "chop_label": "Glass"
        },
        {
          "time": "2026-04-13T18:00",
          "wind_mph": 8.6,
          "wind_dir_deg": 261,
          "gust_mph": 15.7,
          "effective_wind_mph": 4.0,
          "chop_score": 98,
          "chop_label": "Glass"
        }
      ]
    },
    {
      "id": "mid_east",
      "name": "Mid-Lake East",
      "lat": 47.6,
      "lon": -122.082,
      "time": "2026-04-13T14:00",
      "wind_mph": 9.3,
      "wind_dir_deg": 246,
      "gust_mph": 15.7,
      "effective_wind_mph": 9.3,
      "chop_score": 16,
      "chop_label": "Too Rough",
      "hourly": [
        {
          "time": "2026-04-13T14:00",
          "wind_mph": 9.3,
          "wind_dir_deg": 246,
          "gust_mph": 15.7,
          "effective_wind_mph": 9.3,
          "chop_score": 16,
          "chop_label": "Too Rough"
        },
        {
          "time": "2026-04-13T15:00",
          "wind_mph": 7.9,
          "wind_dir_deg": 260,
          "gust_mph": 13.2,
          "effective_wind_mph": 7.9,
          "chop_score": 53,
          "chop_label": "Choppy"
        },
        {
          "time": "2026-04-13T16:00",
          "wind_mph": 7.8,
          "wind_dir_deg": 258,
          "gust_mph": 13.4,
          "effective_wind_mph": 7.8,
          "chop_score": 52,
          "chop_label": "Choppy"
        },
        {
          "time": "2026-04-13T17:00",
          "wind_mph": 9.1,
          "wind_dir_deg": 259,
          "gust_mph": 16.1,
          "effective_wind_mph": 9.1,
          "chop_score": 44,
          "chop_label": "Choppy"
        },
        {
          "time": "2026-04-13T18:00",
          "wind_mph": 8.6,
          "wind_dir_deg": 261,
          "gust_mph": 15.7,
          "effective_wind_mph": 8.6,
          "chop_score": 46,
          "chop_label": "Choppy"
        }
      ]
    },
    {
      "id": "south_central",
      "name": "South Central",
      "lat": 47.58,
      "lon": -122.09,
      "time": "2026-04-13T14:00",
      "wind_mph": 9.1,
      "wind_dir_deg": 245,
      "gust_mph": 15.9,
      "effective_wind_mph": 6.4,
      "chop_score": 89,
      "chop_label": "Glass",
      "hourly": [
        {
          "time": "2026-04-13T14:00",
          "wind_mph": 9.1,
          "wind_dir_deg": 245,
          "gust_mph": 15.9,
          "effective_wind_mph": 6.4,
          "chop_score": 89,
          "chop_label": "Glass"
        },
        {
          "time": "2026-04-13T15:00",
          "wind_mph": 9.1,
          "wind_dir_deg": 253,
          "gust_mph": 15.4,
          "effective_wind_mph": 5.3,
          "chop_score": 91,
          "chop_label": "Glass"
        },
        {
          "time": "2026-04-13T16:00",
          "wind_mph": 9.0,
          "wind_dir_deg": 256,
          "gust_mph": 15.7,
          "effective_wind_mph": 5.2,
          "chop_score": 91,
          "chop_label": "Glass"
        },
        {
          "time": "2026-04-13T17:00",
          "wind_mph": 9.6,
          "wind_dir_deg": 259,
          "gust_mph": 16.8,
          "effective_wind_mph": 5.6,
          "chop_score": 90,
          "chop_label": "Glass"
        },
        {
          "time": "2026-04-13T18:00",
          "wind_mph": 8.6,
          "wind_dir_deg": 261,
          "gust_mph": 15.9,
          "effective_wind_mph": 5.0,
          "chop_score": 91,
          "chop_label": "Glass"
        }
      ]
    },
    {
      "id": "south_end",
      "name": "South End",
      "lat": 47.565,
      "lon": -122.082,
      "time": "2026-04-13T14:00",
      "wind_mph": 8.8,
      "wind_dir_deg": 243,
      "gust_mph": 16.6,
      "effective_wind_mph": 5.6,
      "chop_score": 94,
      "chop_label": "Glass",
      "hourly": [
        {
          "time": "2026-04-13T14:00",
          "wind_mph": 8.8,
          "wind_dir_deg": 243,
          "gust_mph": 16.6,
          "effective_wind_mph": 5.6,
          "chop_score": 94,
          "chop_label": "Glass"
        },
        {
          "time": "2026-04-13T15:00",
          "wind_mph": 9.2,
          "wind_dir_deg": 252,
          "gust_mph": 16.1,
          "effective_wind_mph": 5.3,
          "chop_score": 94,
          "chop_label": "Glass"
        },
        {
          "time": "2026-04-13T16:00",
          "wind_mph": 9.0,
          "wind_dir_deg": 256,
          "gust_mph": 16.1,
          "effective_wind_mph": 5.2,
          "chop_score": 94,
          "chop_label": "Glass"
        },
        {
          "time": "2026-04-13T17:00",
          "wind_mph": 9.3,
          "wind_dir_deg": 260,
          "gust_mph": 17.2,
          "effective_wind_mph": 5.4,
          "chop_score": 94,
          "chop_label": "Glass"
        },
        {
          "time": "2026-04-13T18:00",
          "wind_mph": 8.6,
          "wind_dir_deg": 261,
          "gust_mph": 16.1,
          "effective_wind_mph": 5.0,
          "chop_score": 94,
          "chop_label": "Glass"
        }
      ]
    }
  ],
  "recommendation": {
    "zone_id": "mid_west",
    "zone_name": "The Cove",
    "chop_score": 96,
    "chop_label": "Glass"
  }
}