{
  "generated_at": "2026-04-14T08:02:35",
  "zones": [
    {
      "id": "north",
      "name": "North End",
      "lat": 47.64,
      "lon": -122.092,
      "time": "2026-04-14T08:00",
      "wind_mph": 9.3,
      "wind_dir_deg": 201,
      "gust_mph": 27.5,
      "effective_wind_mph": 9.3,
      "chop_score": 0,
      "chop_label": "Too Rough",
      "hourly": [
        {
          "time": "2026-04-14T08:00",
          "wind_mph": 9.3,
          "wind_dir_deg": 201,
          "gust_mph": 27.5,
          "effective_wind_mph": 9.3,
          "chop_score": 0,
          "chop_label": "Too Rough"
        },
        {
          "time": "2026-04-14T09:00",
          "wind_mph": 9.7,
          "wind_dir_deg": 203,
          "gust_mph": 29.5,
          "effective_wind_mph": 9.7,
          "chop_score": 0,
          "chop_label": "Too Rough"
        },
        {
          "time": "2026-04-14T10:00",
          "wind_mph": 8.9,
          "wind_dir_deg": 212,
          "gust_mph": 28.4,
          "effective_wind_mph": 8.9,
          "chop_score": 0,
          "chop_label": "Too Rough"
        },
        {
          "time": "2026-04-14T11:00",
          "wind_mph": 11.5,
          "wind_dir_deg": 216,
          "gust_mph": 31.1,
          "effective_wind_mph": 11.5,
          "chop_score": 0,
          "chop_label": "Too Rough"
        },
        {
          "time": "2026-04-14T12:00",
          "wind_mph": 13.0,
          "wind_dir_deg": 224,
          "gust_mph": 32.7,
          "effective_wind_mph": 13.0,
          "chop_score": 0,
          "chop_label": "Too Rough"
        }
      ]
    },
    {
      "id": "ne_shore",
      "name": "NE Shore",
      "lat": 47.622,
      "lon": -122.078,
      "time": "2026-04-14T08:00",
      "wind_mph": 9.8,
      "wind_dir_deg": 200,
      "gust_mph": 27.5,
      "effective_wind_mph": 9.8,
      "chop_score": 0,
      "chop_label": "Too Rough",
      "hourly": [
        {
          "time": "2026-04-14T08:00",
          "wind_mph": 9.8,
          "wind_dir_deg": 200,
          "gust_mph": 27.5,
          "effective_wind_mph": 9.8,
          "chop_score": 0,
          "chop_label": "Too Rough"
        },
        {
          "time": "2026-04-14T09:00",
          "wind_mph": 10.1,
          "wind_dir_deg": 202,
          "gust_mph": 30.2,
          "effective_wind_mph": 10.1,
          "chop_score": 0,
          "chop_label": "Too Rough"
        },
        {
          "time": "2026-04-14T10:00",
          "wind_mph": 9.1,
          "wind_dir_deg": 213,
          "gust_mph": 29.3,
          "effective_wind_mph": 9.1,
          "chop_score": 0,
          "chop_label": "Too Rough"
        },
        {
          "time": "2026-04-14T11:00",
          "wind_mph": 12.0,
          "wind_dir_deg": 217,
          "gust_mph": 31.3,
          "effective_wind_mph": 12.0,
          "chop_score": 0,
          "chop_label": "Too Rough"
        },
        {
          "time": "2026-04-14T12:00",
          "wind_mph": 13.0,
          "wind_dir_deg": 225,
          "gust_mph": 32.2,
          "effective_wind_mph": 13.0,
          "chop_score": 0,
          "chop_label": "Too Rough"
        }
      ]
    },
    {
      "id": "mid_west",
      "name": "The Cove",
      "lat": 47.612,
      "lon": -122.102,
      "time": "2026-04-14T08:00",
      "wind_mph": 9.8,
      "wind_dir_deg": 200,
      "gust_mph": 27.5,
      "effective_wind_mph": 9.8,
      "chop_score": 0,
      "chop_label": "Too Rough",
      "hourly": [
        {
          "time": "2026-04-14T08:00",
          "wind_mph": 9.8,
          "wind_dir_deg": 200,
          "gust_mph": 27.5,
          "effective_wind_mph": 9.8,
          "chop_score": 0,
          "chop_label": "Too Rough"
        },
        {
          "time": "2026-04-14T09:00",
          "wind_mph": 10.1,
          "wind_dir_deg": 202,
          "gust_mph": 30.2,
          "effective_wind_mph": 10.1,
          "chop_score": 0,
          "chop_label": "Too Rough"
        },
        {
          "time": "2026-04-14T10:00",
          "wind_mph": 9.1,
          "wind_dir_deg": 213,
          "gust_mph": 29.3,
          "effective_wind_mph": 4.7,
          "chop_score": 94,
          "chop_label": "Glass"
        },
        {
          "time": "2026-04-14T11:00",
          "wind_mph": 12.0,
          "wind_dir_deg": 217,
          "gust_mph": 31.3,
          "effective_wind_mph": 6.2,
          "chop_score": 93,
          "chop_label": "Glass"
        },
        {
          "time": "2026-04-14T12:00",
          "wind_mph": 13.0,
          "wind_dir_deg": 225,
          "gust_mph": 32.2,
          "effective_wind_mph": 6.8,
          "chop_score": 93,
          "chop_label": "Glass"
        }
      ]
    },
    {
      "id": "mid_east",
      "name": "Mid-Lake East",
      "lat": 47.6,
      "lon": -122.082,
      "time": "2026-04-14T08:00",
      "wind_mph": 9.8,
      "wind_dir_deg": 200,
      "gust_mph": 27.5,
      "effective_wind_mph": 9.8,
      "chop_score": 0,
      "chop_label": "Too Rough",
      "hourly": [
        {
          "time": "2026-04-14T08:00",
          "wind_mph": 9.8,
          "wind_dir_deg": 200,
          "gust_mph": 27.5,
          "effective_wind_mph": 9.8,
          "chop_score": 0,
          "chop_label": "Too Rough"
        },
        {
          "time": "2026-04-14T09:00",
          "wind_mph": 10.1,
          "wind_dir_deg": 202,
          "gust_mph": 30.2,
          "effective_wind_mph": 10.1,
          "chop_score": 0,
          "chop_label": "Too Rough"
        },
        {
          "time": "2026-04-14T10:00",
          "wind_mph": 9.1,
          "wind_dir_deg": 213,
          "gust_mph": 29.3,
          "effective_wind_mph": 9.1,
          "chop_score": 0,
          "chop_label": "Too Rough"
        },
        {
          "time": "2026-04-14T11:00",
          "wind_mph": 12.0,
          "wind_dir_deg": 217,
          "gust_mph": 31.3,
          "effective_wind_mph": 12.0,
          "chop_score": 0,
          "chop_label": "Too Rough"
        },
        {
          "time": "2026-04-14T12:00",
          "wind_mph": 13.0,
          "wind_dir_deg": 225,
          "gust_mph": 32.2,
          "effective_wind_mph": 13.0,
          "chop_score": 0,
          "chop_label": "Too Rough"
        }
      ]
    },
    {
      "id": "south_central",
      "name": "South Central",
      "lat": 47.58,
      "lon": -122.09,
      "time": "2026-04-14T08:00",
      "wind_mph": 9.9,
      "wind_dir_deg": 198,
      "gust_mph": 27.5,
      "effective_wind_mph": 8.1,
      "chop_score": 27,
      "chop_label": "Too Rough",
      "hourly": [
        {
          "time": "2026-04-14T08:00",
          "wind_mph": 9.9,
          "wind_dir_deg": 198,
          "gust_mph": 27.5,
          "effective_wind_mph": 8.1,
          "chop_score": 27,
          "chop_label": "Too Rough"
        },
        {
          "time": "2026-04-14T09:00",
          "wind_mph": 10.0,
          "wind_dir_deg": 200,
          "gust_mph": 30.2,
          "effective_wind_mph": 8.2,
          "chop_score": 21,
          "chop_label": "Too Rough"
        },
        {
          "time": "2026-04-14T10:00",
          "wind_mph": 10.2,
          "wind_dir_deg": 212,
          "gust_mph": 30.6,
          "effective_wind_mph": 7.1,
          "chop_score": 81,
          "chop_label": "Glass"
        },
        {
          "time": "2026-04-14T11:00",
          "wind_mph": 12.4,
          "wind_dir_deg": 215,
          "gust_mph": 31.1,
          "effective_wind_mph": 8.7,
          "chop_score": 81,
          "chop_label": "Glass"
        },
        {
          "time": "2026-04-14T12:00",
          "wind_mph": 13.0,
          "wind_dir_deg": 224,
          "gust_mph": 32.0,
          "effective_wind_mph": 9.1,
          "chop_score": 80,
          "chop_label": "Glass"
        }
      ]
    },
    {
      "id": "south_end",
      "name": "South End",
      "lat": 47.565,
      "lon": -122.082,
      "time": "2026-04-14T08:00",
      "wind_mph": 8.6,
      "wind_dir_deg": 200,
      "gust_mph": 27.3,
      "effective_wind_mph": 5.0,
      "chop_score": 94,
      "chop_label": "Glass",
      "hourly": [
        {
          "time": "2026-04-14T08:00",
          "wind_mph": 8.6,
          "wind_dir_deg": 200,
          "gust_mph": 27.3,
          "effective_wind_mph": 5.0,
          "chop_score": 94,
          "chop_label": "Glass"
        },
        {
          "time": "2026-04-14T09:00",
          "wind_mph": 8.1,
          "wind_dir_deg": 199,
          "gust_mph": 29.8,
          "effective_wind_mph": 4.7,
          "chop_score": 93,
          "chop_label": "Glass"
        },
        {
          "time": "2026-04-14T10:00",
          "wind_mph": 10.9,
          "wind_dir_deg": 212,
          "gust_mph": 31.5,
          "effective_wind_mph": 7.0,
          "chop_score": 89,
          "chop_label": "Glass"
        },
        {
          "time": "2026-04-14T11:00",
          "wind_mph": 11.6,
          "wind_dir_deg": 218,
          "gust_mph": 30.9,
          "effective_wind_mph": 7.4,
          "chop_score": 89,
          "chop_label": "Glass"
        },
        {
          "time": "2026-04-14T12:00",
          "wind_mph": 12.5,
          "wind_dir_deg": 224,
          "gust_mph": 31.8,
          "effective_wind_mph": 8.0,
          "chop_score": 89,
          "chop_label": "Glass"
        }
      ]
    }
  ],
  "recommendation": {
    "zone_id": "south_end",
    "zone_name": "South End",
    "chop_score": 94,
    "chop_label": "Glass"
  }
}